bacon/__init__.py
bacon/baconNet.py
bacon/binaryTreeLogicNet.py
bacon/frozonInputToLeaf.py
bacon/inputToLeafSinkhorn.py
bacon/utils.py
bacon/vectorLogicNet.py
bacon/visualization.py
bacon/aggregators/__init__.py
bacon/aggregators/base.py
bacon/aggregators/bool/__init__.py
bacon/aggregators/bool/min_max.py
bacon/aggregators/lsp/__init__.py
bacon/aggregators/lsp/full_weight.py
bacon/aggregators/lsp/half_weight.py
bacon_net-0.3.0.dist-info/METADATA
bacon_net-0.3.0.dist-info/WHEEL
bacon_net-0.3.0.dist-info/licenses/LICENSE
bacon_net-0.3.0.dist-info/RECORD
