Metadata-Version: 2.4
Name: bacon-net
Version: 0.3.0
Summary: BACON: Binary Aggregation Classifier for interpretable decision-making using graded logic.
Project-URL: Homepage, https://example.com/bacon-net
License: Apache-2.0
License-File: LICENSE
Keywords: classifier,explainability,interpretable-ml,logic,pytorch
Classifier: Development Status :: 3 - Alpha
Classifier: Intended Audience :: Developers
Classifier: Intended Audience :: Science/Research
Classifier: License :: OSI Approved :: Apache Software License
Classifier: Operating System :: OS Independent
Classifier: Programming Language :: Python
Classifier: Programming Language :: Python :: 3
Classifier: Programming Language :: Python :: 3.9
Classifier: Programming Language :: Python :: 3.10
Classifier: Programming Language :: Python :: 3.11
Classifier: Programming Language :: Python :: 3.12
Classifier: Topic :: Scientific/Engineering :: Artificial Intelligence
Requires-Python: >=3.9
Requires-Dist: matplotlib>=3.6
Requires-Dist: networkx>=2.8
Requires-Dist: numpy>=1.22
Requires-Dist: pandas>=1.5
Requires-Dist: scikit-learn>=1.1
Requires-Dist: scipy>=1.9
Requires-Dist: seaborn>=0.12
Requires-Dist: torch>=2.0.0
